<annotation>
	<folder>V2_Experimental</folder>
	<filename>IMG_20210907_141955.jpg</filename>
	<path>D:\fredd\Desktop\Projects\Thesis\Thesis_Photos\V2_Experimental\IMG_20210907_141955.jpg</path>
	<source>
		<database>Unknown</database>
	</source>
	<size>
		<width>3000</width>
		<height>4000</height>
		<depth>3</depth>
	</size>
	<segmented>0</segmented>
	<object>
		<name>UFR</name>
		<pose>Unspecified</pose>
		<truncated>0</truncated>
		<difficult>0</difficult>
		<bndbox>
			<xmin>1491</xmin>
			<ymin>2688</ymin>
			<xmax>1531</xmax>
			<ymax>2732</ymax>
		</bndbox>
	</object>
	<object>
		<name>UFR</name>
		<pose>Unspecified</pose>
		<truncated>0</truncated>
		<difficult>0</difficult>
		<bndbox>
			<xmin>1432</xmin>
			<ymin>2618</ymin>
			<xmax>1472</xmax>
			<ymax>2662</ymax>
		</bndbox>
	</object>
	<object>
		<name>UFR</name>
		<pose>Unspecified</pose>
		<truncated>0</truncated>
		<difficult>0</difficult>
		<bndbox>
			<xmin>1388</xmin>
			<ymin>2646</ymin>
			<xmax>1428</xmax>
			<ymax>2690</ymax>
		</bndbox>
	</object>
	<object>
		<name>UFR</name>
		<pose>Unspecified</pose>
		<truncated>0</truncated>
		<difficult>0</difficult>
		<bndbox>
			<xmin>1360</xmin>
			<ymin>2607</ymin>
			<xmax>1400</xmax>
			<ymax>2651</ymax>
		</bndbox>
	</object>
	<object>
		<name>UFR</name>
		<pose>Unspecified</pose>
		<truncated>0</truncated>
		<difficult>0</difficult>
		<bndbox>
			<xmin>1436</xmin>
			<ymin>2554</ymin>
			<xmax>1476</xmax>
			<ymax>2598</ymax>
		</bndbox>
	</object>
	<object>
		<name>UFR</name>
		<pose>Unspecified</pose>
		<truncated>0</truncated>
		<difficult>0</difficult>
		<bndbox>
			<xmin>1507</xmin>
			<ymin>2521</ymin>
			<xmax>1547</xmax>
			<ymax>2565</ymax>
		</bndbox>
	</object>
	<object>
		<name>UFR</name>
		<pose>Unspecified</pose>
		<truncated>0</truncated>
		<difficult>0</difficult>
		<bndbox>
			<xmin>1601</xmin>
			<ymin>2461</ymin>
			<xmax>1641</xmax>
			<ymax>2505</ymax>
		</bndbox>
	</object>
	<object>
		<name>UFR</name>
		<pose>Unspecified</pose>
		<truncated>0</truncated>
		<difficult>0</difficult>
		<bndbox>
			<xmin>2076</xmin>
			<ymin>2382</ymin>
			<xmax>2116</xmax>
			<ymax>2426</ymax>
		</bndbox>
	</object>
	<object>
		<name>UFR</name>
		<pose>Unspecified</pose>
		<truncated>0</truncated>
		<difficult>0</difficult>
		<bndbox>
			<xmin>1400</xmin>
			<ymin>2483</ymin>
			<xmax>1440</xmax>
			<ymax>2527</ymax>
		</bndbox>
	</object>
	<object>
		<name>UFR</name>
		<pose>Unspecified</pose>
		<truncated>0</truncated>
		<difficult>0</difficult>
		<bndbox>
			<xmin>1382</xmin>
			<ymin>2539</ymin>
			<xmax>1422</xmax>
			<ymax>2583</ymax>
		</bndbox>
	</object>
	<object>
		<name>UFR</name>
		<pose>Unspecified</pose>
		<truncated>0</truncated>
		<difficult>0</difficult>
		<bndbox>
			<xmin>1473</xmin>
			<ymin>2397</ymin>
			<xmax>1513</xmax>
			<ymax>2441</ymax>
		</bndbox>
	</object>
	<object>
		<name>UFR</name>
		<pose>Unspecified</pose>
		<truncated>0</truncated>
		<difficult>0</difficult>
		<bndbox>
			<xmin>1631</xmin>
			<ymin>2268</ymin>
			<xmax>1671</xmax>
			<ymax>2312</ymax>
		</bndbox>
	</object>
	<object>
		<name>UFR</name>
		<pose>Unspecified</pose>
		<truncated>0</truncated>
		<difficult>0</difficult>
		<bndbox>
			<xmin>1560</xmin>
			<ymin>2223</ymin>
			<xmax>1600</xmax>
			<ymax>2267</ymax>
		</bndbox>
	</object>
	<object>
		<name>UFR</name>
		<pose>Unspecified</pose>
		<truncated>0</truncated>
		<difficult>0</difficult>
		<bndbox>
			<xmin>1345</xmin>
			<ymin>2272</ymin>
			<xmax>1385</xmax>
			<ymax>2316</ymax>
		</bndbox>
	</object>
	<object>
		<name>UFR</name>
		<pose>Unspecified</pose>
		<truncated>0</truncated>
		<difficult>0</difficult>
		<bndbox>
			<xmin>1291</xmin>
			<ymin>2293</ymin>
			<xmax>1331</xmax>
			<ymax>2337</ymax>
		</bndbox>
	</object>
	<object>
		<name>UFR</name>
		<pose>Unspecified</pose>
		<truncated>0</truncated>
		<difficult>0</difficult>
		<bndbox>
			<xmin>1163</xmin>
			<ymin>2315</ymin>
			<xmax>1203</xmax>
			<ymax>2359</ymax>
		</bndbox>
	</object>
	<object>
		<name>UFR</name>
		<pose>Unspecified</pose>
		<truncated>0</truncated>
		<difficult>0</difficult>
		<bndbox>
			<xmin>1088</xmin>
			<ymin>2246</ymin>
			<xmax>1128</xmax>
			<ymax>2290</ymax>
		</bndbox>
	</object>
	<object>
		<name>UFR</name>
		<pose>Unspecified</pose>
		<truncated>0</truncated>
		<difficult>0</difficult>
		<bndbox>
			<xmin>1011</xmin>
			<ymin>2322</ymin>
			<xmax>1051</xmax>
			<ymax>2366</ymax>
		</bndbox>
	</object>
	<object>
		<name>UFR</name>
		<pose>Unspecified</pose>
		<truncated>0</truncated>
		<difficult>0</difficult>
		<bndbox>
			<xmin>832</xmin>
			<ymin>2229</ymin>
			<xmax>872</xmax>
			<ymax>2273</ymax>
		</bndbox>
	</object>
	<object>
		<name>UFR</name>
		<pose>Unspecified</pose>
		<truncated>0</truncated>
		<difficult>0</difficult>
		<bndbox>
			<xmin>765</xmin>
			<ymin>2069</ymin>
			<xmax>805</xmax>
			<ymax>2113</ymax>
		</bndbox>
	</object>
	<object>
		<name>UFR</name>
		<pose>Unspecified</pose>
		<truncated>0</truncated>
		<difficult>0</difficult>
		<bndbox>
			<xmin>613</xmin>
			<ymin>1961</ymin>
			<xmax>653</xmax>
			<ymax>2005</ymax>
		</bndbox>
	</object>
	<object>
		<name>UFR</name>
		<pose>Unspecified</pose>
		<truncated>0</truncated>
		<difficult>0</difficult>
		<bndbox>
			<xmin>689</xmin>
			<ymin>2430</ymin>
			<xmax>729</xmax>
			<ymax>2474</ymax>
		</bndbox>
	</object>
	<object>
		<name>UFR</name>
		<pose>Unspecified</pose>
		<truncated>0</truncated>
		<difficult>0</difficult>
		<bndbox>
			<xmin>996</xmin>
			<ymin>2640</ymin>
			<xmax>1036</xmax>
			<ymax>2684</ymax>
		</bndbox>
	</object>
	<object>
		<name>UFR</name>
		<pose>Unspecified</pose>
		<truncated>0</truncated>
		<difficult>0</difficult>
		<bndbox>
			<xmin>816</xmin>
			<ymin>2756</ymin>
			<xmax>856</xmax>
			<ymax>2800</ymax>
		</bndbox>
	</object>
	<object>
		<name>UFR</name>
		<pose>Unspecified</pose>
		<truncated>0</truncated>
		<difficult>0</difficult>
		<bndbox>
			<xmin>756</xmin>
			<ymin>2877</ymin>
			<xmax>796</xmax>
			<ymax>2921</ymax>
		</bndbox>
	</object>
	<object>
		<name>UFR</name>
		<pose>Unspecified</pose>
		<truncated>0</truncated>
		<difficult>0</difficult>
		<bndbox>
			<xmin>712</xmin>
			<ymin>2947</ymin>
			<xmax>752</xmax>
			<ymax>2991</ymax>
		</bndbox>
	</object>
	<object>
		<name>UFR</name>
		<pose>Unspecified</pose>
		<truncated>0</truncated>
		<difficult>0</difficult>
		<bndbox>
			<xmin>649</xmin>
			<ymin>2941</ymin>
			<xmax>689</xmax>
			<ymax>2985</ymax>
		</bndbox>
	</object>
	<object>
		<name>UFR</name>
		<pose>Unspecified</pose>
		<truncated>0</truncated>
		<difficult>0</difficult>
		<bndbox>
			<xmin>618</xmin>
			<ymin>2920</ymin>
			<xmax>655</xmax>
			<ymax>2965</ymax>
		</bndbox>
	</object>
	<object>
		<name>UFR</name>
		<pose>Unspecified</pose>
		<truncated>0</truncated>
		<difficult>0</difficult>
		<bndbox>
			<xmin>664</xmin>
			<ymin>3010</ymin>
			<xmax>701</xmax>
			<ymax>3055</ymax>
		</bndbox>
	</object>
	<object>
		<name>UFR</name>
		<pose>Unspecified</pose>
		<truncated>0</truncated>
		<difficult>0</difficult>
		<bndbox>
			<xmin>735</xmin>
			<ymin>2998</ymin>
			<xmax>772</xmax>
			<ymax>3043</ymax>
		</bndbox>
	</object>
	<object>
		<name>UFR</name>
		<pose>Unspecified</pose>
		<truncated>0</truncated>
		<difficult>0</difficult>
		<bndbox>
			<xmin>501</xmin>
			<ymin>3083</ymin>
			<xmax>538</xmax>
			<ymax>3128</ymax>
		</bndbox>
	</object>
	<object>
		<name>UFR</name>
		<pose>Unspecified</pose>
		<truncated>0</truncated>
		<difficult>0</difficult>
		<bndbox>
			<xmin>595</xmin>
			<ymin>3196</ymin>
			<xmax>632</xmax>
			<ymax>3241</ymax>
		</bndbox>
	</object>
	<object>
		<name>UFR</name>
		<pose>Unspecified</pose>
		<truncated>0</truncated>
		<difficult>0</difficult>
		<bndbox>
			<xmin>1126</xmin>
			<ymin>3128</ymin>
			<xmax>1163</xmax>
			<ymax>3173</ymax>
		</bndbox>
	</object>
	<object>
		<name>UFR</name>
		<pose>Unspecified</pose>
		<truncated>0</truncated>
		<difficult>0</difficult>
		<bndbox>
			<xmin>1338</xmin>
			<ymin>3095</ymin>
			<xmax>1375</xmax>
			<ymax>3140</ymax>
		</bndbox>
	</object>
	<object>
		<name>UFR</name>
		<pose>Unspecified</pose>
		<truncated>0</truncated>
		<difficult>0</difficult>
		<bndbox>
			<xmin>1103</xmin>
			<ymin>3506</ymin>
			<xmax>1140</xmax>
			<ymax>3551</ymax>
		</bndbox>
	</object>
	<object>
		<name>UFR</name>
		<pose>Unspecified</pose>
		<truncated>0</truncated>
		<difficult>0</difficult>
		<bndbox>
			<xmin>1093</xmin>
			<ymin>3555</ymin>
			<xmax>1130</xmax>
			<ymax>3600</ymax>
		</bndbox>
	</object>
	<object>
		<name>UFR</name>
		<pose>Unspecified</pose>
		<truncated>0</truncated>
		<difficult>0</difficult>
		<bndbox>
			<xmin>1276</xmin>
			<ymin>3474</ymin>
			<xmax>1313</xmax>
			<ymax>3519</ymax>
		</bndbox>
	</object>
	<object>
		<name>UFR</name>
		<pose>Unspecified</pose>
		<truncated>0</truncated>
		<difficult>0</difficult>
		<bndbox>
			<xmin>1252</xmin>
			<ymin>3604</ymin>
			<xmax>1289</xmax>
			<ymax>3649</ymax>
		</bndbox>
	</object>
	<object>
		<name>UFR</name>
		<pose>Unspecified</pose>
		<truncated>0</truncated>
		<difficult>0</difficult>
		<bndbox>
			<xmin>1204</xmin>
			<ymin>3724</ymin>
			<xmax>1241</xmax>
			<ymax>3769</ymax>
		</bndbox>
	</object>
	<object>
		<name>UFR</name>
		<pose>Unspecified</pose>
		<truncated>0</truncated>
		<difficult>0</difficult>
		<bndbox>
			<xmin>1407</xmin>
			<ymin>3590</ymin>
			<xmax>1444</xmax>
			<ymax>3635</ymax>
		</bndbox>
	</object>
	<object>
		<name>UFR</name>
		<pose>Unspecified</pose>
		<truncated>0</truncated>
		<difficult>0</difficult>
		<bndbox>
			<xmin>1464</xmin>
			<ymin>3720</ymin>
			<xmax>1501</xmax>
			<ymax>3765</ymax>
		</bndbox>
	</object>
	<object>
		<name>UFR</name>
		<pose>Unspecified</pose>
		<truncated>0</truncated>
		<difficult>0</difficult>
		<bndbox>
			<xmin>1151</xmin>
			<ymin>3874</ymin>
			<xmax>1188</xmax>
			<ymax>3919</ymax>
		</bndbox>
	</object>
	<object>
		<name>UFR</name>
		<pose>Unspecified</pose>
		<truncated>0</truncated>
		<difficult>0</difficult>
		<bndbox>
			<xmin>826</xmin>
			<ymin>3495</ymin>
			<xmax>863</xmax>
			<ymax>3540</ymax>
		</bndbox>
	</object>
	<object>
		<name>UFR</name>
		<pose>Unspecified</pose>
		<truncated>0</truncated>
		<difficult>0</difficult>
		<bndbox>
			<xmin>1836</xmin>
			<ymin>3190</ymin>
			<xmax>1873</xmax>
			<ymax>3235</ymax>
		</bndbox>
	</object>
	<object>
		<name>UFR</name>
		<pose>Unspecified</pose>
		<truncated>0</truncated>
		<difficult>0</difficult>
		<bndbox>
			<xmin>1820</xmin>
			<ymin>3045</ymin>
			<xmax>1857</xmax>
			<ymax>3090</ymax>
		</bndbox>
	</object>
	<object>
		<name>UFR</name>
		<pose>Unspecified</pose>
		<truncated>0</truncated>
		<difficult>0</difficult>
		<bndbox>
			<xmin>1912</xmin>
			<ymin>3471</ymin>
			<xmax>1949</xmax>
			<ymax>3516</ymax>
		</bndbox>
	</object>
	<object>
		<name>UFR</name>
		<pose>Unspecified</pose>
		<truncated>0</truncated>
		<difficult>0</difficult>
		<bndbox>
			<xmin>1888</xmin>
			<ymin>3521</ymin>
			<xmax>1925</xmax>
			<ymax>3566</ymax>
		</bndbox>
	</object>
	<object>
		<name>UFR</name>
		<pose>Unspecified</pose>
		<truncated>0</truncated>
		<difficult>0</difficult>
		<bndbox>
			<xmin>1780</xmin>
			<ymin>3711</ymin>
			<xmax>1817</xmax>
			<ymax>3756</ymax>
		</bndbox>
	</object>
	<object>
		<name>UFR</name>
		<pose>Unspecified</pose>
		<truncated>0</truncated>
		<difficult>0</difficult>
		<bndbox>
			<xmin>2282</xmin>
			<ymin>3547</ymin>
			<xmax>2337</xmax>
			<ymax>3609</ymax>
		</bndbox>
	</object>
	<object>
		<name>UFR</name>
		<pose>Unspecified</pose>
		<truncated>0</truncated>
		<difficult>0</difficult>
		<bndbox>
			<xmin>2250</xmin>
			<ymin>3408</ymin>
			<xmax>2294</xmax>
			<ymax>3462</ymax>
		</bndbox>
	</object>
	<object>
		<name>UFR</name>
		<pose>Unspecified</pose>
		<truncated>0</truncated>
		<difficult>0</difficult>
		<bndbox>
			<xmin>1541</xmin>
			<ymin>2863</ymin>
			<xmax>1585</xmax>
			<ymax>2917</ymax>
		</bndbox>
	</object>
	<object>
		<name>UFR</name>
		<pose>Unspecified</pose>
		<truncated>0</truncated>
		<difficult>0</difficult>
		<bndbox>
			<xmin>1655</xmin>
			<ymin>2618</ymin>
			<xmax>1699</xmax>
			<ymax>2672</ymax>
		</bndbox>
	</object>
	<object>
		<name>UFR</name>
		<pose>Unspecified</pose>
		<truncated>0</truncated>
		<difficult>0</difficult>
		<bndbox>
			<xmin>2085</xmin>
			<ymin>2422</ymin>
			<xmax>2117</xmax>
			<ymax>2454</ymax>
		</bndbox>
	</object>
	<object>
		<name>UFR</name>
		<pose>Unspecified</pose>
		<truncated>0</truncated>
		<difficult>0</difficult>
		<bndbox>
			<xmin>2123</xmin>
			<ymin>2460</ymin>
			<xmax>2155</xmax>
			<ymax>2492</ymax>
		</bndbox>
	</object>
	<object>
		<name>UFR</name>
		<pose>Unspecified</pose>
		<truncated>0</truncated>
		<difficult>0</difficult>
		<bndbox>
			<xmin>2184</xmin>
			<ymin>2289</ymin>
			<xmax>2216</xmax>
			<ymax>2321</ymax>
		</bndbox>
	</object>
	<object>
		<name>UFR</name>
		<pose>Unspecified</pose>
		<truncated>0</truncated>
		<difficult>0</difficult>
		<bndbox>
			<xmin>2314</xmin>
			<ymin>2334</ymin>
			<xmax>2346</xmax>
			<ymax>2366</ymax>
		</bndbox>
	</object>
	<object>
		<name>UFR</name>
		<pose>Unspecified</pose>
		<truncated>0</truncated>
		<difficult>0</difficult>
		<bndbox>
			<xmin>2512</xmin>
			<ymin>3024</ymin>
			<xmax>2570</xmax>
			<ymax>3079</ymax>
		</bndbox>
	</object>
	<object>
		<name>UFR</name>
		<pose>Unspecified</pose>
		<truncated>0</truncated>
		<difficult>0</difficult>
		<bndbox>
			<xmin>1942</xmin>
			<ymin>2153</ymin>
			<xmax>1984</xmax>
			<ymax>2199</ymax>
		</bndbox>
	</object>
	<object>
		<name>UFR</name>
		<pose>Unspecified</pose>
		<truncated>0</truncated>
		<difficult>0</difficult>
		<bndbox>
			<xmin>1513</xmin>
			<ymin>2104</ymin>
			<xmax>1557</xmax>
			<ymax>2147</ymax>
		</bndbox>
	</object>
	<object>
		<name>UFR</name>
		<pose>Unspecified</pose>
		<truncated>0</truncated>
		<difficult>0</difficult>
		<bndbox>
			<xmin>1738</xmin>
			<ymin>2207</ymin>
			<xmax>1780</xmax>
			<ymax>2253</ymax>
		</bndbox>
	</object>
	<object>
		<name>UFR</name>
		<pose>Unspecified</pose>
		<truncated>0</truncated>
		<difficult>0</difficult>
		<bndbox>
			<xmin>1627</xmin>
			<ymin>1902</ymin>
			<xmax>1671</xmax>
			<ymax>1945</ymax>
		</bndbox>
	</object>
	<object>
		<name>UFR</name>
		<pose>Unspecified</pose>
		<truncated>0</truncated>
		<difficult>0</difficult>
		<bndbox>
			<xmin>1831</xmin>
			<ymin>1894</ymin>
			<xmax>1875</xmax>
			<ymax>1937</ymax>
		</bndbox>
	</object>
	<object>
		<name>UFR</name>
		<pose>Unspecified</pose>
		<truncated>0</truncated>
		<difficult>0</difficult>
		<bndbox>
			<xmin>1571</xmin>
			<ymin>1737</ymin>
			<xmax>1615</xmax>
			<ymax>1780</ymax>
		</bndbox>
	</object>
	<object>
		<name>UFR</name>
		<pose>Unspecified</pose>
		<truncated>0</truncated>
		<difficult>0</difficult>
		<bndbox>
			<xmin>1074</xmin>
			<ymin>1756</ymin>
			<xmax>1118</xmax>
			<ymax>1799</ymax>
		</bndbox>
	</object>
	<object>
		<name>UFR</name>
		<pose>Unspecified</pose>
		<truncated>0</truncated>
		<difficult>0</difficult>
		<bndbox>
			<xmin>1345</xmin>
			<ymin>2046</ymin>
			<xmax>1389</xmax>
			<ymax>2089</ymax>
		</bndbox>
	</object>
	<object>
		<name>UFR</name>
		<pose>Unspecified</pose>
		<truncated>0</truncated>
		<difficult>0</difficult>
		<bndbox>
			<xmin>1159</xmin>
			<ymin>2272</ymin>
			<xmax>1203</xmax>
			<ymax>2315</ymax>
		</bndbox>
	</object>
	<object>
		<name>UFR</name>
		<pose>Unspecified</pose>
		<truncated>0</truncated>
		<difficult>0</difficult>
		<bndbox>
			<xmin>488</xmin>
			<ymin>2484</ymin>
			<xmax>532</xmax>
			<ymax>2527</ymax>
		</bndbox>
	</object>
	<object>
		<name>UFR</name>
		<pose>Unspecified</pose>
		<truncated>0</truncated>
		<difficult>0</difficult>
		<bndbox>
			<xmin>586</xmin>
			<ymin>2147</ymin>
			<xmax>630</xmax>
			<ymax>2190</ymax>
		</bndbox>
	</object>
	<object>
		<name>FR</name>
		<pose>Unspecified</pose>
		<truncated>0</truncated>
		<difficult>0</difficult>
		<bndbox>
			<xmin>1536</xmin>
			<ymin>2060</ymin>
			<xmax>1580</xmax>
			<ymax>2103</ymax>
		</bndbox>
	</object>
	<object>
		<name>FR</name>
		<pose>Unspecified</pose>
		<truncated>0</truncated>
		<difficult>0</difficult>
		<bndbox>
			<xmin>2274</xmin>
			<ymin>2862</ymin>
			<xmax>2341</xmax>
			<ymax>2939</ymax>
		</bndbox>
	</object>
	<object>
		<name>UFR</name>
		<pose>Unspecified</pose>
		<truncated>0</truncated>
		<difficult>0</difficult>
		<bndbox>
			<xmin>967</xmin>
			<ymin>1579</ymin>
			<xmax>1011</xmax>
			<ymax>1622</ymax>
		</bndbox>
	</object>
	<object>
		<name>UFR</name>
		<pose>Unspecified</pose>
		<truncated>0</truncated>
		<difficult>0</difficult>
		<bndbox>
			<xmin>766</xmin>
			<ymin>1547</ymin>
			<xmax>810</xmax>
			<ymax>1590</ymax>
		</bndbox>
	</object>
	<object>
		<name>UFR</name>
		<pose>Unspecified</pose>
		<truncated>0</truncated>
		<difficult>0</difficult>
		<bndbox>
			<xmin>1478</xmin>
			<ymin>1363</ymin>
			<xmax>1522</xmax>
			<ymax>1406</ymax>
		</bndbox>
	</object>
	<object>
		<name>UFR</name>
		<pose>Unspecified</pose>
		<truncated>0</truncated>
		<difficult>0</difficult>
		<bndbox>
			<xmin>1615</xmin>
			<ymin>2061</ymin>
			<xmax>1659</xmax>
			<ymax>2104</ymax>
		</bndbox>
	</object>
	<object>
		<name>UFR</name>
		<pose>Unspecified</pose>
		<truncated>0</truncated>
		<difficult>0</difficult>
		<bndbox>
			<xmin>1874</xmin>
			<ymin>1993</ymin>
			<xmax>1918</xmax>
			<ymax>2036</ymax>
		</bndbox>
	</object>
	<object>
		<name>UFR</name>
		<pose>Unspecified</pose>
		<truncated>0</truncated>
		<difficult>0</difficult>
		<bndbox>
			<xmin>1884</xmin>
			<ymin>2144</ymin>
			<xmax>1922</xmax>
			<ymax>2180</ymax>
		</bndbox>
	</object>
	<object>
		<name>UFR</name>
		<pose>Unspecified</pose>
		<truncated>0</truncated>
		<difficult>0</difficult>
		<bndbox>
			<xmin>1168</xmin>
			<ymin>2224</ymin>
			<xmax>1206</xmax>
			<ymax>2260</ymax>
		</bndbox>
	</object>
	<object>
		<name>UFR</name>
		<pose>Unspecified</pose>
		<truncated>0</truncated>
		<difficult>0</difficult>
		<bndbox>
			<xmin>949</xmin>
			<ymin>2170</ymin>
			<xmax>987</xmax>
			<ymax>2206</ymax>
		</bndbox>
	</object>
	<object>
		<name>UFR</name>
		<pose>Unspecified</pose>
		<truncated>0</truncated>
		<difficult>0</difficult>
		<bndbox>
			<xmin>1126</xmin>
			<ymin>1758</ymin>
			<xmax>1163</xmax>
			<ymax>1801</ymax>
		</bndbox>
	</object>
	<object>
		<name>FR</name>
		<pose>Unspecified</pose>
		<truncated>0</truncated>
		<difficult>0</difficult>
		<bndbox>
			<xmin>2659</xmin>
			<ymin>2817</ymin>
			<xmax>2726</xmax>
			<ymax>2894</ymax>
		</bndbox>
	</object>
	<object>
		<name>FR</name>
		<pose>Unspecified</pose>
		<truncated>0</truncated>
		<difficult>0</difficult>
		<bndbox>
			<xmin>1561</xmin>
			<ymin>3094</ymin>
			<xmax>1606</xmax>
			<ymax>3145</ymax>
		</bndbox>
	</object>
	<object>
		<name>FR</name>
		<pose>Unspecified</pose>
		<truncated>0</truncated>
		<difficult>0</difficult>
		<bndbox>
			<xmin>1144</xmin>
			<ymin>2894</ymin>
			<xmax>1189</xmax>
			<ymax>2945</ymax>
		</bndbox>
	</object>
	<object>
		<name>FR</name>
		<pose>Unspecified</pose>
		<truncated>0</truncated>
		<difficult>0</difficult>
		<bndbox>
			<xmin>1852</xmin>
			<ymin>3307</ymin>
			<xmax>1912</xmax>
			<ymax>3351</ymax>
		</bndbox>
	</object>
	<object>
		<name>FR</name>
		<pose>Unspecified</pose>
		<truncated>0</truncated>
		<difficult>0</difficult>
		<bndbox>
			<xmin>558</xmin>
			<ymin>3254</ymin>
			<xmax>611</xmax>
			<ymax>3306</ymax>
		</bndbox>
	</object>
	<object>
		<name>FR</name>
		<pose>Unspecified</pose>
		<truncated>0</truncated>
		<difficult>0</difficult>
		<bndbox>
			<xmin>518</xmin>
			<ymin>3305</ymin>
			<xmax>571</xmax>
			<ymax>3357</ymax>
		</bndbox>
	</object>
	<object>
		<name>UFR</name>
		<pose>Unspecified</pose>
		<truncated>0</truncated>
		<difficult>0</difficult>
		<bndbox>
			<xmin>36</xmin>
			<ymin>3326</ymin>
			<xmax>98</xmax>
			<ymax>3383</ymax>
		</bndbox>
	</object>
	<object>
		<name>UFR</name>
		<pose>Unspecified</pose>
		<truncated>0</truncated>
		<difficult>0</difficult>
		<bndbox>
			<xmin>243</xmin>
			<ymin>3424</ymin>
			<xmax>305</xmax>
			<ymax>3481</ymax>
		</bndbox>
	</object>
	<object>
		<name>UFR</name>
		<pose>Unspecified</pose>
		<truncated>0</truncated>
		<difficult>0</difficult>
		<bndbox>
			<xmin>113</xmin>
			<ymin>3518</ymin>
			<xmax>175</xmax>
			<ymax>3575</ymax>
		</bndbox>
	</object>
	<object>
		<name>FR</name>
		<pose>Unspecified</pose>
		<truncated>0</truncated>
		<difficult>0</difficult>
		<bndbox>
			<xmin>1914</xmin>
			<ymin>1829</ymin>
			<xmax>1960</xmax>
			<ymax>1882</ymax>
		</bndbox>
	</object>
	<object>
		<name>FR</name>
		<pose>Unspecified</pose>
		<truncated>0</truncated>
		<difficult>0</difficult>
		<bndbox>
			<xmin>1370</xmin>
			<ymin>1627</ymin>
			<xmax>1414</xmax>
			<ymax>1661</ymax>
		</bndbox>
	</object>
	<object>
		<name>UFR</name>
		<pose>Unspecified</pose>
		<truncated>0</truncated>
		<difficult>0</difficult>
		<bndbox>
			<xmin>2001</xmin>
			<ymin>1681</ymin>
			<xmax>2037</xmax>
			<ymax>1722</ymax>
		</bndbox>
	</object>
	<object>
		<name>FR</name>
		<pose>Unspecified</pose>
		<truncated>0</truncated>
		<difficult>0</difficult>
		<bndbox>
			<xmin>1192</xmin>
			<ymin>1566</ymin>
			<xmax>1243</xmax>
			<ymax>1606</ymax>
		</bndbox>
	</object>
	<object>
		<name>FR</name>
		<pose>Unspecified</pose>
		<truncated>0</truncated>
		<difficult>0</difficult>
		<bndbox>
			<xmin>1059</xmin>
			<ymin>1920</ymin>
			<xmax>1102</xmax>
			<ymax>1954</ymax>
		</bndbox>
	</object>
	<object>
		<name>FR</name>
		<pose>Unspecified</pose>
		<truncated>0</truncated>
		<difficult>0</difficult>
		<bndbox>
			<xmin>1311</xmin>
			<ymin>1848</ymin>
			<xmax>1349</xmax>
			<ymax>1896</ymax>
		</bndbox>
	</object>
	<object>
		<name>FR</name>
		<pose>Unspecified</pose>
		<truncated>0</truncated>
		<difficult>0</difficult>
		<bndbox>
			<xmin>1082</xmin>
			<ymin>2116</ymin>
			<xmax>1123</xmax>
			<ymax>2168</ymax>
		</bndbox>
	</object>
	<object>
		<name>FR</name>
		<pose>Unspecified</pose>
		<truncated>0</truncated>
		<difficult>0</difficult>
		<bndbox>
			<xmin>1140</xmin>
			<ymin>2475</ymin>
			<xmax>1181</xmax>
			<ymax>2527</ymax>
		</bndbox>
	</object>
	<object>
		<name>FR</name>
		<pose>Unspecified</pose>
		<truncated>0</truncated>
		<difficult>0</difficult>
		<bndbox>
			<xmin>873</xmin>
			<ymin>2488</ymin>
			<xmax>921</xmax>
			<ymax>2533</ymax>
		</bndbox>
	</object>
	<object>
		<name>FR</name>
		<pose>Unspecified</pose>
		<truncated>0</truncated>
		<difficult>0</difficult>
		<bndbox>
			<xmin>1254</xmin>
			<ymin>2800</ymin>
			<xmax>1301</xmax>
			<ymax>2830</ymax>
		</bndbox>
	</object>
	<object>
		<name>FR</name>
		<pose>Unspecified</pose>
		<truncated>0</truncated>
		<difficult>0</difficult>
		<bndbox>
			<xmin>936</xmin>
			<ymin>2939</ymin>
			<xmax>983</xmax>
			<ymax>2969</ymax>
		</bndbox>
	</object>
	<object>
		<name>FR</name>
		<pose>Unspecified</pose>
		<truncated>0</truncated>
		<difficult>0</difficult>
		<bndbox>
			<xmin>1327</xmin>
			<ymin>2990</ymin>
			<xmax>1369</xmax>
			<ymax>3028</ymax>
		</bndbox>
	</object>
	<object>
		<name>FR</name>
		<pose>Unspecified</pose>
		<truncated>0</truncated>
		<difficult>0</difficult>
		<bndbox>
			<xmin>1806</xmin>
			<ymin>2782</ymin>
			<xmax>1843</xmax>
			<ymax>2830</ymax>
		</bndbox>
	</object>
	<object>
		<name>FR</name>
		<pose>Unspecified</pose>
		<truncated>0</truncated>
		<difficult>0</difficult>
		<bndbox>
			<xmin>2053</xmin>
			<ymin>2751</ymin>
			<xmax>2094</xmax>
			<ymax>2776</ymax>
		</bndbox>
	</object>
	<object>
		<name>FR</name>
		<pose>Unspecified</pose>
		<truncated>0</truncated>
		<difficult>0</difficult>
		<bndbox>
			<xmin>2406</xmin>
			<ymin>2653</ymin>
			<xmax>2453</xmax>
			<ymax>2694</ymax>
		</bndbox>
	</object>
	<object>
		<name>FR</name>
		<pose>Unspecified</pose>
		<truncated>0</truncated>
		<difficult>0</difficult>
		<bndbox>
			<xmin>1994</xmin>
			<ymin>2459</ymin>
			<xmax>2030</xmax>
			<ymax>2492</ymax>
		</bndbox>
	</object>
	<object>
		<name>FR</name>
		<pose>Unspecified</pose>
		<truncated>0</truncated>
		<difficult>0</difficult>
		<bndbox>
			<xmin>2182</xmin>
			<ymin>3078</ymin>
			<xmax>2219</xmax>
			<ymax>3126</ymax>
		</bndbox>
	</object>
	<object>
		<name>UFR</name>
		<pose>Unspecified</pose>
		<truncated>0</truncated>
		<difficult>0</difficult>
		<bndbox>
			<xmin>2305</xmin>
			<ymin>2151</ymin>
			<xmax>2337</xmax>
			<ymax>2183</ymax>
		</bndbox>
	</object>
	<object>
		<name>FR</name>
		<pose>Unspecified</pose>
		<truncated>0</truncated>
		<difficult>0</difficult>
		<bndbox>
			<xmin>2257</xmin>
			<ymin>1898</ymin>
			<xmax>2293</xmax>
			<ymax>1931</ymax>
		</bndbox>
	</object>
	<object>
		<name>FR</name>
		<pose>Unspecified</pose>
		<truncated>0</truncated>
		<difficult>0</difficult>
		<bndbox>
			<xmin>472</xmin>
			<ymin>2007</ymin>
			<xmax>513</xmax>
			<ymax>2059</ymax>
		</bndbox>
	</object>
	<object>
		<name>FR</name>
		<pose>Unspecified</pose>
		<truncated>0</truncated>
		<difficult>0</difficult>
		<bndbox>
			<xmin>351</xmin>
			<ymin>2104</ymin>
			<xmax>376</xmax>
			<ymax>2142</ymax>
		</bndbox>
	</object>
	<object>
		<name>FR</name>
		<pose>Unspecified</pose>
		<truncated>0</truncated>
		<difficult>0</difficult>
		<bndbox>
			<xmin>185</xmin>
			<ymin>2316</ymin>
			<xmax>218</xmax>
			<ymax>2353</ymax>
		</bndbox>
	</object>
	<object>
		<name>FR</name>
		<pose>Unspecified</pose>
		<truncated>0</truncated>
		<difficult>0</difficult>
		<bndbox>
			<xmin>324</xmin>
			<ymin>2775</ymin>
			<xmax>370</xmax>
			<ymax>2812</ymax>
		</bndbox>
	</object>
	<object>
		<name>FR</name>
		<pose>Unspecified</pose>
		<truncated>0</truncated>
		<difficult>0</difficult>
		<bndbox>
			<xmin>525</xmin>
			<ymin>2746</ymin>
			<xmax>568</xmax>
			<ymax>2793</ymax>
		</bndbox>
	</object>
</annotation>
